api/__init__.py
api/scan_api.py
api/toolkit_api.py
api/uleska_api.py
model/__init__.py
model/failure_thresholds.py
model/tool.py
model/toolkit.py
model/toolkit_and_tools.py
service/__init__.py
service/report.py
service/scan.py
service/toolkit.py
test/__init__.py
test/test_report.py
test/test_scan.py
test/test_scan_api.py
test/test_toolkit.py
test/test_toolkit_api.py
test/test_uleska_api.py
uleska_automate-0.12.data/scripts/uleska-automate
uleska_automate-0.12.dist-info/LICENSE
uleska_automate-0.12.dist-info/METADATA
uleska_automate-0.12.dist-info/WHEEL
uleska_automate-0.12.dist-info/top_level.txt
uleska_automate-0.12.dist-info/RECORD
