Metadata-Version: 2.1
Name: uleska-automate
Version: 0.12
Summary: A CLI for the Uleska DevSecOps Platform
Home-page: https://github.com/uleska/uleska-automate
Author: Gary Robinson
Author-email: gary.robinson@uleska.com
License: UNKNOWN
Platform: UNKNOWN
Classifier: Programming Language :: Python :: 3
Classifier: License :: OSI Approved :: GNU General Public License v3 (GPLv3)
Classifier: Operating System :: OS Independent
License-File: LICENSE
Requires-Dist: requests
